csvcomparer/__init__.py
csvcomparer/__main__.py
csvcomparer/csvcomparer.py
csvcomparer-0.1.0.dist-info/entry_points.txt
csvcomparer-0.1.0.dist-info/LICENSE.txt
csvcomparer-0.1.0.dist-info/WHEEL
csvcomparer-0.1.0.dist-info/METADATA
csvcomparer-0.1.0.dist-info/RECORD
