Metadata-Version: 2.1
Name: csvcomparer
Version: 0.1.0
Summary: Compare delimited files that share a common key.
Home-page: https://github.com/bergsmith/csvcomparer
License: MIT
Keywords: compare,csv,diff,difference,comparer
Author: Ryan Bergsmith
Author-email: ryguydev@gmail.com
Requires-Python: >=3.8,<4.0
Classifier: License :: OSI Approved :: MIT License
Classifier: Programming Language :: Python :: 3
Classifier: Programming Language :: Python :: 3.10
Classifier: Programming Language :: Python :: 3.8
Classifier: Programming Language :: Python :: 3.9
Requires-Dist: pandas (>=1.4.2,<2.0.0)
Project-URL: Documentation, https://csvcomparer.readthedocs.io/en/latest/
Project-URL: Repository, https://github.com/bergsmith/csvcomparer
